pybu/__init__.py
pybu/exceptions.py
pybu/fields.py
pybu/model.py
pybu-0.1.dist-info/DESCRIPTION.rst
pybu-0.1.dist-info/METADATA
pybu-0.1.dist-info/RECORD
pybu-0.1.dist-info/WHEEL
pybu-0.1.dist-info/metadata.json
pybu-0.1.dist-info/top_level.txt
