Metadata-Version: 2.0
Name: pybu
Version: 0.1
Summary: Simple Data Objects
Home-page: https://github.com/ekiro/pybu
Author: Piotr Karkut
Author-email: karkucik@gmail.com
License: MIT License
Platform: any
